agni/__init__.py
agni-0.0.1.dist-info/LICENSE
agni-0.0.1.dist-info/METADATA
agni-0.0.1.dist-info/WHEEL
agni-0.0.1.dist-info/top_level.txt
agni-0.0.1.dist-info/RECORD
