Metadata-Version: 2.1
Name: agni
Version: 0.0.1
Summary: AGNI (AutoGrader with Nice Interface), a Python assignment grading tool and a companion to Codepost. (Work in progress)
Home-page: https://github.com/d3vp/agni
Author: Deven Parekh
Author-email: deven.parekh@mail.mcgill.ca
License: UNKNOWN
Platform: UNKNOWN
Classifier: Programming Language :: Python :: 3
Classifier: License :: OSI Approved :: MIT License
Classifier: Operating System :: OS Independent
Requires-Python: >=3.7
